{
    "type": "service_account",
    "project_id": "onlifin",
    "private_key_id": "a695beb7c2433717f936b6e3e8e870f184603525",
    "private_key": "-----BEGIN PRIVATE KEY-----\nMIIEvgIBADANBgkqhkiG9w0BAQEFAASCBKgwggSkAgEAAoIBAQD8/+EeReppCoAh\niw57R83WzJPe5UM2f5w8tBsXveym1zv6KlsLDUgpcgqILoPCg58sKgQHQuvAjf87\nYPsd1JBo9D2cK2pOuyPh>
    "client_email": "laravel-integrator-sa@onlifin.iam.gserviceaccount.com",
    "client_id": "116377511738778907136",
    "auth_uri": "https://accounts.google.com/o/oauth2/auth",
    "token_uri": "https://oauth2.googleapis.com/token",
    "auth_provider_x509_cert_url": "https://www.googleapis.com/oauth2/v1/certs",
    "client_x509_cert_url": "https://www.googleapis.com/robot/v1/metadata/x509/laravel-integrator-sa%40onlifin.iam.gserviceaccount.com",
    "universe_domain": "googleapis.com"
  }
  
  
  
  
  